mzt_http_utils/HTTPUtils.py
mzt_http_utils/__init__.py
mzt_http_utils-1.0.dist-info/LICENSE
mzt_http_utils-1.0.dist-info/METADATA
mzt_http_utils-1.0.dist-info/WHEEL
mzt_http_utils-1.0.dist-info/top_level.txt
mzt_http_utils-1.0.dist-info/RECORD
