Metadata-Version: 2.1
Name: mzt-http-utils
Version: 1.0
Summary: UNKNOWN
Home-page: https://github.com/rmizuuti/mzt_http_utils
Author: Roberto Mizuuti
Author-email: rmizuuti@gmail.com
License: UNKNOWN
Platform: UNKNOWN
Classifier: Programming Language :: Python :: 3
Classifier: License :: OSI Approved :: MIT License
Classifier: Operating System :: OS Independent
Requires-Python: >=3.6
Requires-Dist: requests
